kvaut
