Metadata-Version: 1.0
Name: kvaut
Version: 0.0.17
Summary: Automation for BDD testing Kivy apps
Home-page: UNKNOWN
Author: Gary Johnson
Author-email: gary@gjtt.com
License: MIT License
Platform: UNKNOWN
